LICENSE
README.md
setup.cfg
setup.py
lasertools_tracefit/__init__.py
lasertools_tracefit/ga.py
lasertools_tracefit/helpers.py
lasertools_tracefit/local.py
lasertools_tracefit.egg-info/PKG-INFO
lasertools_tracefit.egg-info/SOURCES.txt
lasertools_tracefit.egg-info/dependency_links.txt
lasertools_tracefit.egg-info/requires.txt
lasertools_tracefit.egg-info/top_level.txt
lasertools_tracefit/models/__init__.py
lasertools_tracefit/models/arbitrarypolynomial.py
lasertools_tracefit/models/base.py
lasertools_tracefit/models/gaussianpolynomial.py
lasertools_tracefit/resources/__init__.py
lasertools_tracefit/resources/colormap_jetwhite.py
lasertools_tracefit/resources/outplot_ga.py